apitester/__init__.py
apitester/oauth2_app.py
mautic/__init__.py
mautic/api.py
mautic/assets.py
mautic/campaigns.py
mautic/categories.py
mautic/companies.py
mautic/company_fields.py
mautic/contact_fields.py
mautic/contacts.py
mautic/data.py
mautic/dynamic_contents.py
mautic/emails.py
mautic/exceptions.py
mautic/files.py
mautic/forms.py
mautic/notes.py
mautic/notifications.py
mautic/pages.py
mautic/point_triggers.py
mautic/points.py
mautic/reports.py
mautic/roles.py
mautic/segments.py
mautic/smses.py
mautic/stages.py
mautic/stats.py
mautic/users.py
mautic/utils.py
mautic-0.2.0.dist-info/DESCRIPTION.rst
mautic-0.2.0.dist-info/METADATA
mautic-0.2.0.dist-info/RECORD
mautic-0.2.0.dist-info/WHEEL
mautic-0.2.0.dist-info/metadata.json
mautic-0.2.0.dist-info/top_level.txt
tests/__init__.py
tests/test_mautic_python.py
